cpunk_mongo/__init__.py
cpunk_mongo/db/__init__.py
cpunk_mongo-0.5.0.dist-info/METADATA
cpunk_mongo-0.5.0.dist-info/WHEEL
cpunk_mongo-0.5.0.dist-info/RECORD
