Metadata-Version: 2.1
Name: cpunk-mongo
Version: 0.5.0
Summary: 
Author: matfonseca
Author-email: mfonseca@fi.uba.ar
Requires-Python: >=3.7,<4.0
Classifier: Programming Language :: Python :: 3
Classifier: Programming Language :: Python :: 3.7
Classifier: Programming Language :: Python :: 3.8
Classifier: Programming Language :: Python :: 3.9
Classifier: Programming Language :: Python :: 3.10
Classifier: Programming Language :: Python :: 3.11
Requires-Dist: pymongo (>=4.3.3,<5.0.0)
